{
    "data": [
      {
        "url1": "php/corsProxy.php?topic=albtal",
        "url2": "data/karlsruhe/cityclim-example.json",
        "url": "https://dashboard.daten.city/php/corsProxy.php?topic=albtal,sonnenbad,kaiserplatz",
        "license": "CC-BY-4.0",
        "name": "Wetter Karlsruhe",
        "format": "json",
        "xaxis": "measured_at",
        "columns": [
          "temperature","humidity","irradiation"
        ],
        "classes": [
        ]
      }
    ],
    "chart": {
      "updating": false
    },
    "controls": {
      "range": {
        "present": false,
        "min": 1,
        "max": 100
      },
      "type": {
        "present": false,
        "options": [
          "line",
          "bar"
        ]
      },
      "stacked": {
        "present": false
      },
      "dataswitch": {
        "present": false
      },
      "animate": {
        "present": false
      }
    }
  }

